pysquagg/__init__.py
pysquagg/pysquagg.py
pysquagg-1.1.0.dist-info/METADATA
pysquagg-1.1.0.dist-info/WHEEL
pysquagg-1.1.0.dist-info/licenses/LICENSE
pysquagg-1.1.0.dist-info/RECORD
