Metadata-Version: 2.4
Name: pysquagg
Version: 1.1.0
Summary: A simple library for performing Square Root Decomposition and Aggregation
Project-URL: Source code, https://github.com/danielenricocahall/pysquagg
Author-email: Daniel Cahall <danielenricocahall@gmail.com>
License-File: LICENSE
Requires-Python: >=3.10
